kgpy/__init__.py
kgpy/__init__test.py
kgpy/_data_test.py
kgpy/_filter_test.py
kgpy/_interpolation_test.py
kgpy/_labeled_test.py
kgpy/_matrix_test.py
kgpy/_test_sun.py
kgpy/_uncertainty_test.py
kgpy/_units_test.py
kgpy/_vector_test.py
kgpy/atmosphere.py
kgpy/chianti.py
kgpy/data.py
kgpy/dxf.py
kgpy/filter.py
kgpy/format.py
kgpy/geometry.py
kgpy/grid.py
kgpy/interpolation.py
kgpy/labeled.py
kgpy/matrix.py
kgpy/mixin.py
kgpy/model.py
kgpy/polynomial.py
kgpy/sun.py
kgpy/uncertainty.py
kgpy/units.py
kgpy/vector.py
kgpy/fft/__init__.py
kgpy/fft/freq.py
kgpy/fft/power.py
kgpy/fft/random.py
kgpy/fft/test_powerspec.py
kgpy/img/__init__.py
kgpy/img/_spikes_test.py
kgpy/img/mask.py
kgpy/img/spikes.py
kgpy/img/GeneralizedMedian/3blob.png
kgpy/img/GeneralizedMedian/Generalized Median.ipynb
kgpy/img/GeneralizedMedian/README.txt
kgpy/img/GeneralizedMedian/__init__.py
kgpy/img/GeneralizedMedian/gm.py
kgpy/img/GeneralizedMedian/notebook.tex
kgpy/img/GeneralizedMedian/output_6_1.png
kgpy/img/GeneralizedMedian/output_7_1.png
kgpy/img/GeneralizedMedian/output_8_1.png
kgpy/img/GeneralizedMedian/zmom2d.pro
kgpy/img/GeneralizedMedian/zmom2d_test.pro
kgpy/img/GeneralizedMedian/.ipynb_checkpoints/Generalized Median-checkpoint.ipynb
kgpy/img/GeneralizedMedian/.ipynb_checkpoints/Plotting Images Tutorial-checkpoint.ipynb
kgpy/img/coalignment/__init__.py
kgpy/img/coalignment/image_coalignment.py
kgpy/img/coalignment/test_image_coalignment.py
kgpy/img/examples/Plotting Images Tutorial.ipynb
kgpy/img/examples/README.txt
kgpy/img/examples/.ipynb_checkpoints/Plotting Images Tutorial-checkpoint.ipynb
kgpy/io/__init__.py
kgpy/io/fits.py
kgpy/latex/__init__.py
kgpy/latex/aas.py
kgpy/moment/__init__.py
kgpy/moment/percentile.py
kgpy/multiprocess_tools/__init__.py
kgpy/multiprocess_tools/mp_wrapper.py
kgpy/nsroc/__init__.py
kgpy/nsroc/sparcs.py
kgpy/obs/__init__.py
kgpy/obs/__init__test.py
kgpy/obs/spectral.py
kgpy/observatories/__init__.py
kgpy/observatories/cds/__init__.py
kgpy-0.1.1.dist-info/METADATA
kgpy-0.1.1.dist-info/WHEEL
kgpy-0.1.1.dist-info/top_level.txt
kgpy-0.1.1.dist-info/RECORD
